allutils/__init__.py
allutils/utils.py
package/__init__.py
package/package.py
mypackage_divyamtalreja-0.0.2.dist-info/LICENSE
mypackage_divyamtalreja-0.0.2.dist-info/METADATA
mypackage_divyamtalreja-0.0.2.dist-info/WHEEL
mypackage_divyamtalreja-0.0.2.dist-info/top_level.txt
mypackage_divyamtalreja-0.0.2.dist-info/RECORD
