Metadata-Version: 2.1
Name: mypackage-divyamtalreja
Version: 0.0.2
Summary: implementation of  perceptron
Home-page: https://github.com/divyamtalreja/mypackage
Author: divyamtalreja
Author-email: divyamtalreja16@gmail.com
License: UNKNOWN
Project-URL: Bug Tracker, https://github.com/divyamtalreja/mypackage/issues
Platform: UNKNOWN
Classifier: Programming Language :: Python :: 3
Classifier: License :: OSI Approved :: MIT License
Classifier: Operating System :: OS Independent
Requires-Python: >=3.7
License-File: LICENSE
Requires-Dist: numpy
Requires-Dist: pandas
